bianary_decision_parameter/__init__.py
bianary_decision_parameter-0.2.dist-info/LICENCE.txt
bianary_decision_parameter-0.2.dist-info/METADATA
bianary_decision_parameter-0.2.dist-info/WHEEL
bianary_decision_parameter-0.2.dist-info/top_level.txt
bianary_decision_parameter-0.2.dist-info/RECORD
